Metadata-Version: 2.1
Name: E4sy
Version: 0.0.1
Summary: Simplify Your Code, With Custom Commands.
Home-page: UNKNOWN
Author: Fred
Author-email: unknown@gmail.com
License: UNKNOWN
Keywords: python,simple,easy,e4sy,custom
Platform: UNKNOWN
Classifier: Development Status :: 1 - Planning
Classifier: Intended Audience :: Developers
Classifier: Programming Language :: Python :: 3
Classifier: Operating System :: Unix
Classifier: Operating System :: MacOS :: MacOS X
Classifier: Operating System :: Microsoft :: Windows
